speechcapture/__init__.py
speechcapture/recorder.py
speechcapture-0.5.0.dist-info/LICENSE
speechcapture-0.5.0.dist-info/METADATA
speechcapture-0.5.0.dist-info/WHEEL
speechcapture-0.5.0.dist-info/RECORD
