Metadata-Version: 2.3
Name: speechcapture
Version: 0.5.0
Summary: An easy to use library for recording and saving speech audio
License: MIT License
Keywords: speech,audio,record
Author: Bilal Darwish
Author-email: darwish.b.bilal@gmail.com
Requires-Python: >=3.8
Classifier: License :: Other/Proprietary License
Classifier: Programming Language :: Python :: 3
Classifier: Programming Language :: Python :: 3.8
Classifier: Programming Language :: Python :: 3.9
Classifier: Programming Language :: Python :: 3.10
Classifier: Programming Language :: Python :: 3.11
Classifier: Programming Language :: Python :: 3.12
Classifier: Programming Language :: Python :: 3.13
Requires-Dist: numpy (>=1.20)
Requires-Dist: pyaudio (>=0.2.11)
